{
  "id": "imprint",
  "name": "imprint",
  "layouts": {
    "Imprint": {
      "autoGenerated": "false",
      "description": "Cyboard Imprint",
      "layout": [
        { "row": 4,  "col": 5, "x":    0,   "y":   0 },
        { "row": 4,  "col": 4, "x":    1,   "y":   0 },
        { "row": 4,  "col": 3, "x":    2,   "y":   0 },
        { "row": 4,  "col": 2, "x":    3,   "y":   0 },
        { "row": 4,  "col": 1, "x":    4,   "y":   0 },
        { "row": 4,  "col": 0, "x":    5,   "y":   0 },
        { "row": 11, "col": 0, "x": 11.5,  "y":   0 },
        { "row": 11, "col": 1, "x": 12.5,  "y":   0 },
        { "row": 11, "col": 2, "x": 13.5,  "y":   0 },
        { "row": 11, "col": 3, "x": 14.5,  "y":   0 },
        { "row": 11, "col": 4, "x": 15.5,  "y":   0 },
        { "row": 11, "col": 5, "x": 16.5,  "y":   0 },

        { "row": 3,  "col": 5, "x":    0,   "y":   1 },
        { "row": 3,  "col": 4, "x":    1,   "y":   1 },
        { "row": 3,  "col": 3, "x":    2,   "y":   1 },
        { "row": 3,  "col": 2, "x":    3,   "y":   1 },
        { "row": 3,  "col": 1, "x":    4,   "y":   1 },
        { "row": 3,  "col": 0, "x":    5,   "y":   1 },
        { "row": 10, "col": 0, "x": 11.5,  "y":   1 },
        { "row": 10, "col": 1, "x": 12.5,  "y":   1 },
        { "row": 10, "col": 2, "x": 13.5,  "y":   1 },
        { "row": 10, "col": 3, "x": 14.5,  "y":   1 },
        { "row": 10, "col": 4, "x": 15.5,  "y":   1 },
        { "row": 10, "col": 5, "x": 16.5,  "y":   1 },

        { "row": 2,  "col": 5, "x":    0,   "y":   2 },
        { "row": 2,  "col": 4, "x":    1,   "y":   2 },
        { "row": 2,  "col": 3, "x":    2,   "y":   2 },
        { "row": 2,  "col": 2, "x":    3,   "y":   2 },
        { "row": 2,  "col": 1, "x":    4,   "y":   2 },
        { "row": 2,  "col": 0, "x":    5,   "y":   2 },
        { "row": 9,  "col": 0, "x": 11.5,  "y":   2 },
        { "row": 9,  "col": 1, "x": 12.5,  "y":   2 },
        { "row": 9,  "col": 2, "x": 13.5,  "y":   2 },
        { "row": 9,  "col": 3, "x": 14.5,  "y":   2 },
        { "row": 9,  "col": 4, "x": 15.5,  "y":   2 },
        { "row": 9,  "col": 5, "x": 16.5,  "y":   2 },

        { "row": 1,  "col": 3, "x":    2,   "y":   3 },
        { "row": 1,  "col": 2, "x":    3,   "y":   3 },
        { "row": 8,  "col": 2, "x": 13.5,  "y":   3 },
        { "row": 8,  "col": 3, "x": 14.5,  "y":   3 },

        { "row": 0,  "col": 3, "x":  5.5,  "y": 5.5 },
        { "row": 0,  "col": 2, "x":  6.5,  "y": 5.5 },
        { "row": 0,  "col": 1, "x":  7.5,  "y": 5.5 },
        { "row": 7,  "col": 1, "x":    9,  "y": 5.5 },
        { "row": 7,  "col": 2, "x":   10,  "y": 5.5 },
        { "row": 7,  "col": 3, "x":   11,  "y": 5.5 },

        { "row": 0,  "col": 7, "x":  5.5,  "y": 6.5 },
        { "row": 0,  "col": 6, "x":  6.5,  "y": 6.5 },
        { "row": 0,  "col": 5, "x":  7.5,  "y": 6.5 },
        { "row": 7,  "col": 5, "x":    9,  "y": 6.5 },
        { "row": 7,  "col": 6, "x":   10,  "y": 6.5 },
        { "row": 7,  "col": 7, "x":   11,  "y": 6.5 }
      ]
    }
  },
  "sensors": []
}
